config/__init__.py
config/config.py
config/hardcodedpaths.py
config/properties.py
config_jderobot-1.0.0.dist-info/METADATA
config_jderobot-1.0.0.dist-info/RECORD
config_jderobot-1.0.0.dist-info/WHEEL
config_jderobot-1.0.0.dist-info/top_level.txt
