Metadata-Version: 2.1
Name: config-jderobot
Version: 1.0.0
Summary: config utils package for jderobot project
Home-page: https://github.com/JdeRobot/JdeRobot
Author: aitormf
Author-email: aitor.martinez.fernandez@gmail.com
License: UNKNOWN
Platform: UNKNOWN
Classifier: Programming Language :: Python
Classifier: License :: OSI Approved :: MIT License
Classifier: Operating System :: OS Independent
Requires-Dist: pyyaml
